LICENSE
MANIFEST.in
README.md
setup.py
core/PPA.py
core/__init__.py
core/stream.py
laorm.egg-info/PKG-INFO
laorm.egg-info/SOURCES.txt
laorm.egg-info/dependency_links.txt
laorm.egg-info/requires.txt
laorm.egg-info/top_level.txt