Metadata-Version: 2.1
Name: laorm
Version: 1.1.0
Summary: A python async orm tool
Home-page: https://github.com/mryzhou/laorm
Author: larry
Author-email: 176286171@qq.com
Classifier: Programming Language :: Python :: 3.10
Classifier: License :: OSI Approved :: Apache Software License
Classifier: Operating System :: OS Independent
Provides-Extra: fastapi
Provides-Extra: flask
License-File: LICENSE
